Workbook

Sheet Instructions
A1: Paper trading workbook — Indian equities (NSE / BSE)
A3: 1. Settings — Set starting capital and charge assumptions.
A4: 2. Trade Log — Log every BUY and SELL (one row per fill). Use the same Position ID for entry and exit.
A5: 3. Open Positions — Auto view of symbols still held (net qty > 0).
A6: 4. Closed Trades — Enter exit row with Position ID; realized P&L is calculated.
A7: 5. Summary — Cash, exposure, and performance metrics.
A9: Tips:
A10: • Symbol: use NSE tickers (e.g. RELIANCE, TCS, JINDALSTEL).
A11: • Segment: Equity Delivery or Equity Intraday (affects STT).
A12: • For a swing trade: BUY row Position ID = T001, SELL row same ID = T001.
A13: • LTP (last traded price) on Open Positions is manual — update for mark-to-market.
A15: Regenerate this file: python build_paper_trading_sheet.py
A16: File location: /Users/admin/Desktop/Codebase/ri/test/paper_trading_india.xlsx

Sheet Settings
A1: Indian stock market — paper trading settings
B3: Parameter | C3: Value | D3: Notes
B4: Starting capital (₹) | C4: 500000 | D4: Virtual cash for paper trading
B5: Brokerage per order (₹) | C5: 20 | D5: Typical discount broker flat fee
B6: GST on brokerage (%) | C6: 0.18 | D6: 18% on brokerage
B7: STT — delivery sell (%) | C7: 0.001 | D7: 0.1% on sell turnover
B8: STT — intraday sell (%) | C8: 0.00025 | D8: 0.025% on sell turnover
B9: Exchange txn charge (%) | C9: 3.45e-05 | D9: NSE equity ~0.00345% each side
B10: SEBI fee (%) | C10: 1e-06 | D10: ₹10 per crore (approx)
B11: Stamp duty — buy (%) | C11: 0.00015 | D11: Varies by state; default ~0.015%
B12: DP charges — delivery sell (₹) | C12: 15.93 | D12: Per sell delivery scrip (approx)
B13: Currency | C13: INR
B14: Default exchange | C14: NSE | D14: NSE or BSE
A16: Charge formulas use Settings!$C$4:$C$13. Edit values above to match your broker.

Sheet Trade Log
A1: Trade # | B1: Date | C1: Symbol | D1: Exchange | E1: Segment | F1: Side | G1: Qty | H1: Price (₹) | I1: Position ID | J1: Notes | K1: Gross (₹) | L1: Brokerage (₹) | M1: STT (₹) | N1: Exch+SEBI (₹) | O1: Stamp (₹) | P1: GST (₹) | Q1: DP (₹) | R1: Total charges (₹) | S1: Net cash flow (₹)
A2: =IF(G2="","",ROW()-1) | B2: 2026-05-27 | C2: JINDALSTEL | D2: NSE | E2: Equity Delivery | F2: BUY | G2: 50 | H2: 1205 | I2: T001 | J2: Support rejection entry | K2: =IF(G2="","",G2*H2) | L2: =IF(G2="","",Settings!$C$5) | M2: =IF(G2="","",IF(F2="SELL",K2*IF(E2="Equity Intraday",Settings!$C$8,Settings!$C$7),0)) | N2: =IF(G2="","",K2*(Settings!$C$9+Settings!$C$10)) | O2: =IF(G2="","",IF(F2="BUY",K2*Settings!$C$11,0)) | P2: =IF(G2="","",L2*Settings!$C$6) | Q2: =IF(G2="","",IF(AND(F2="SELL",E2="Equity Delivery"),Settings!$C$13,0)) | R2: =IF(G2="","",SUM(L2:Q2)) | S2: =IF(G2="","",IF(F2="BUY",-(K2+R2),K2-R2))
A3: =IF(G3="","",ROW()-1) | B3: 2026-05-29 | C3: JINDALSTEL | D3: NSE | E3: Equity Delivery | F3: SELL | G3: 50 | H3: 1222 | I3: T001 | J3: Resistance exit | K3: =IF(G3="","",G3*H3) | L3: =IF(G3="","",Settings!$C$5) | M3: =IF(G3="","",IF(F3="SELL",K3*IF(E3="Equity Intraday",Settings!$C$8,Settings!$C$7),0)) | N3: =IF(G3="","",K3*(Settings!$C$9+Settings!$C$10)) | O3: =IF(G3="","",IF(F3="BUY",K3*Settings!$C$11,0)) | P3: =IF(G3="","",L3*Settings!$C$6) | Q3: =IF(G3="","",IF(AND(F3="SELL",E3="Equity Delivery"),Settings!$C$13,0)) | R3: =IF(G3="","",SUM(L3:Q3)) | S3: =IF(G3="","",IF(F3="BUY",-(K3+R3),K3-R3))
A4: =IF(G4="","",ROW()-1) | K4: =IF(G4="","",G4*H4) | L4: =IF(G4="","",Settings!$C$5) | M4: =IF(G4="","",IF(F4="SELL",K4*IF(E4="Equity Intraday",Settings!$C$8,Settings!$C$7),0)) | N4: =IF(G4="","",K4*(Settings!$C$9+Settings!$C$10)) | O4: =IF(G4="","",IF(F4="BUY",K4*Settings!$C$11,0)) | P4: =IF(G4="","",L4*Settings!$C$6) | Q4: =IF(G4="","",IF(AND(F4="SELL",E4="Equity Delivery"),Settings!$C$13,0)) | R4: =IF(G4="","",SUM(L4:Q4)) | S4: =IF(G4="","",IF(F4="BUY",-(K4+R4),K4-R4))
A5: =IF(G5="","",ROW()-1) | K5: =IF(G5="","",G5*H5) | L5: =IF(G5="","",Settings!$C$5) | M5: =IF(G5="","",IF(F5="SELL",K5*IF(E5="Equity Intraday",Settings!$C$8,Settings!$C$7),0)) | N5: =IF(G5="","",K5*(Settings!$C$9+Settings!$C$10)) | O5: =IF(G5="","",IF(F5="BUY",K5*Settings!$C$11,0)) | P5: =IF(G5="","",L5*Settings!$C$6) | Q5: =IF(G5="","",IF(AND(F5="SELL",E5="Equity Delivery"),Settings!$C$13,0)) | R5: =IF(G5="","",SUM(L5:Q5)) | S5: =IF(G5="","",IF(F5="BUY",-(K5+R5),K5-R5))
A6: =IF(G6="","",ROW()-1) | K6: =IF(G6="","",G6*H6) | L6: =IF(G6="","",Settings!$C$5) | M6: =IF(G6="","",IF(F6="SELL",K6*IF(E6="Equity Intraday",Settings!$C$8,Settings!$C$7),0)) | N6: =IF(G6="","",K6*(Settings!$C$9+Settings!$C$10)) | O6: =IF(G6="","",IF(F6="BUY",K6*Settings!$C$11,0)) | P6: =IF(G6="","",L6*Settings!$C$6) | Q6: =IF(G6="","",IF(AND(F6="SELL",E6="Equity Delivery"),Settings!$C$13,0)) | R6: =IF(G6="","",SUM(L6:Q6)) | S6: =IF(G6="","",IF(F6="BUY",-(K6+R6),K6-R6))
A7: =IF(G7="","",ROW()-1) | K7: =IF(G7="","",G7*H7) | L7: =IF(G7="","",Settings!$C$5) | M7: =IF(G7="","",IF(F7="SELL",K7*IF(E7="Equity Intraday",Settings!$C$8,Settings!$C$7),0)) | N7: =IF(G7="","",K7*(Settings!$C$9+Settings!$C$10)) | O7: =IF(G7="","",IF(F7="BUY",K7*Settings!$C$11,0)) | P7: =IF(G7="","",L7*Settings!$C$6) | Q7: =IF(G7="","",IF(AND(F7="SELL",E7="Equity Delivery"),Settings!$C$13,0)) | R7: =IF(G7="","",SUM(L7:Q7)) | S7: =IF(G7="","",IF(F7="BUY",-(K7+R7),K7-R7))
A8: =IF(G8="","",ROW()-1) | K8: =IF(G8="","",G8*H8) | L8: =IF(G8="","",Settings!$C$5) | M8: =IF(G8="","",IF(F8="SELL",K8*IF(E8="Equity Intraday",Settings!$C$8,Settings!$C$7),0)) | N8: =IF(G8="","",K8*(Settings!$C$9+Settings!$C$10)) | O8: =IF(G8="","",IF(F8="BUY",K8*Settings!$C$11,0)) | P8: =IF(G8="","",L8*Settings!$C$6) | Q8: =IF(G8="","",IF(AND(F8="SELL",E8="Equity Delivery"),Settings!$C$13,0)) | R8: =IF(G8="","",SUM(L8:Q8)) | S8: =IF(G8="","",IF(F8="BUY",-(K8+R8),K8-R8))
A9: =IF(G9="","",ROW()-1) | K9: =IF(G9="","",G9*H9) | L9: =IF(G9="","",Settings!$C$5) | M9: =IF(G9="","",IF(F9="SELL",K9*IF(E9="Equity Intraday",Settings!$C$8,Settings!$C$7),0)) | N9: =IF(G9="","",K9*(Settings!$C$9+Settings!$C$10)) | O9: =IF(G9="","",IF(F9="BUY",K9*Settings!$C$11,0)) | P9: =IF(G9="","",L9*Settings!$C$6) | Q9: =IF(G9="","",IF(AND(F9="SELL",E9="Equity Delivery"),Settings!$C$13,0)) | R9: =IF(G9="","",SUM(L9:Q9)) | S9: =IF(G9="","",IF(F9="BUY",-(K9+R9),K9-R9))
A10: =IF(G10="","",ROW()-1) | K10: =IF(G10="","",G10*H10) | L10: =IF(G10="","",Settings!$C$5) | M10: =IF(G10="","",IF(F10="SELL",K10*IF(E10="Equity Intraday",Settings!$C$8,Settings!$C$7),0)) | N10: =IF(G10="","",K10*(Settings!$C$9+Settings!$C$10)) | O10: =IF(G10="","",IF(F10="BUY",K10*Settings!$C$11,0)) | P10: =IF(G10="","",L10*Settings!$C$6) | Q10: =IF(G10="","",IF(AND(F10="SELL",E10="Equity Delivery"),Settings!$C$13,0)) | R10: =IF(G10="","",SUM(L10:Q10)) | S10: =IF(G10="","",IF(F10="BUY",-(K10+R10),K10-R10))
A11: =IF(G11="","",ROW()-1) | K11: =IF(G11="","",G11*H11) | L11: =IF(G11="","",Settings!$C$5) | M11: =IF(G11="","",IF(F11="SELL",K11*IF(E11="Equity Intraday",Settings!$C$8,Settings!$C$7),0)) | N11: =IF(G11="","",K11*(Settings!$C$9+Settings!$C$10)) | O11: =IF(G11="","",IF(F11="BUY",K11*Settings!$C$11,0)) | P11: =IF(G11="","",L11*Settings!$C$6) | Q11: =IF(G11="","",IF(AND(F11="SELL",E11="Equity Delivery"),Settings!$C$13,0)) | R11: =IF(G11="","",SUM(L11:Q11)) | S11: =IF(G11="","",IF(F11="BUY",-(K11+R11),K11-R11))
A12: =IF(G12="","",ROW()-1) | K12: =IF(G12="","",G12*H12) | L12: =IF(G12="","",Settings!$C$5) | M12: =IF(G12="","",IF(F12="SELL",K12*IF(E12="Equity Intraday",Settings!$C$8,Settings!$C$7),0)) | N12: =IF(G12="","",K12*(Settings!$C$9+Settings!$C$10)) | O12: =IF(G12="","",IF(F12="BUY",K12*Settings!$C$11,0)) | P12: =IF(G12="","",L12*Settings!$C$6) | Q12: =IF(G12="","",IF(AND(F12="SELL",E12="Equity Delivery"),Settings!$C$13,0)) | R12: =IF(G12="","",SUM(L12:Q12)) | S12: =IF(G12="","",IF(F12="BUY",-(K12+R12),K12-R12))
A13: =IF(G13="","",ROW()-1) | K13: =IF(G13="","",G13*H13) | L13: =IF(G13="","",Settings!$C$5) | M13: =IF(G13="","",IF(F13="SELL",K13*IF(E13="Equity Intraday",Settings!$C$8,Settings!$C$7),0)) | N13: =IF(G13="","",K13*(Settings!$C$9+Settings!$C$10)) | O13: =IF(G13="","",IF(F13="BUY",K13*Settings!$C$11,0)) | P13: =IF(G13="","",L13*Settings!$C$6) | Q13: =IF(G13="","",IF(AND(F13="SELL",E13="Equity Delivery"),Settings!$C$13,0)) | R13: =IF(G13="","",SUM(L13:Q13)) | S13: =IF(G13="","",IF(F13="BUY",-(K13+R13),K13-R13))
A14: =IF(G14="","",ROW()-1) | K14: =IF(G14="","",G14*H14) | L14: =IF(G14="","",Settings!$C$5) | M14: =IF(G14="","",IF(F14="SELL",K14*IF(E14="Equity Intraday",Settings!$C$8,Settings!$C$7),0)) | N14: =IF(G14="","",K14*(Settings!$C$9+Settings!$C$10)) | O14: =IF(G14="","",IF(F14="BUY",K14*Settings!$C$11,0)) | P14: =IF(G14="","",L14*Settings!$C$6) | Q14: =IF(G14="","",IF(AND(F14="SELL",E14="Equity Delivery"),Settings!$C$13,0)) | R14: =IF(G14="","",SUM(L14:Q14)) | S14: =IF(G14="","",IF(F14="BUY",-(K14+R14),K14-R14))
A15: =IF(G15="","",ROW()-1) | K15: =IF(G15="","",G15*H15) | L15: =IF(G15="","",Settings!$C$5) | M15: =IF(G15="","",IF(F15="SELL",K15*IF(E15="Equity Intraday",Settings!$C$8,Settings!$C$7),0)) | N15: =IF(G15="","",K15*(Settings!$C$9+Settings!$C$10)) | O15: =IF(G15="","",IF(F15="BUY",K15*Settings!$C$11,0)) | P15: =IF(G15="","",L15*Settings!$C$6) | Q15: =IF(G15="","",IF(AND(F15="SELL",E15="Equity Delivery"),Settings!$C$13,0)) | R15: =IF(G15="","",SUM(L15:Q15)) | S15: =IF(G15="","",IF(F15="BUY",-(K15+R15),K15-R15))
... A502: =IF(G502="","",ROW()-1) | K502: =IF(G502="","",G502*H502) | L502: =IF(G502="","",Settings!$C$5) | M502: =IF(G502="","",IF(F502="SELL",K502*IF(E502="Equity Intraday",Settings!$C$8,Settings!$C$7),0)) | N502: =IF(G502="","",K502*(Settings!$C$9+Settings!$C$10)) | O502: =IF(G502="","",IF(F502="BUY",K502*Settings!$C$11,0)) | P502: =IF(G502="","",L502*Settings!$C$6) | Q502: =IF(G502="","",IF(AND(F502="SELL",E502="Equity Delivery"),Settings!$C$13,0)) | R502: =IF(G502="","",SUM(L502:Q502)) | S502: =IF(G502="","",IF(F502="BUY",-(K502+R502),K502-R502))

Sheet Open Positions
A1: Open positions (net qty > 0 from Trade Log)
A3: Symbol | B3: Exchange | C3: Segment | D3: Qty held | E3: Avg cost (₹) | F3: Cost value (₹) | G3: LTP (₹) — update manually | H3: Market value (₹) | I3: Unrealized P&L (₹) | J3: Unrealized %
A4: List symbols you hold (one per row); sample:
A5: JINDALSTEL | B5: =IF(A5="","",INDEX('Trade Log'!D:D,MATCH(A5,'Trade Log'!C:C,0))) | C5: =IF(A5="","",INDEX('Trade Log'!E:E,MATCH(A5,'Trade Log'!C:C,0))) | D5: =IF(A5="","",SUMIFS('Trade Log'!G:G,'Trade Log'!C:C,A5,'Trade Log'!F:F,"BUY")-SUMIFS('Trade Log'!G:G,'Trade Log'!C:C,A5,'Trade Log'!F:F,"SELL")) | E5: =IF(D5<=0,"",SUMIFS('Trade Log'!K:K,'Trade Log'!C:C,A5,'Trade Log'!F:F,"BUY")/SUMIFS('Trade Log'!G:G,'Trade Log'!C:C,A5,'Trade Log'!F:F,"BUY")) | F5: =IF(D5<=0,"",D5*E5) | H5: =IF(D5<=0,"",D5*G5) | I5: =IF(D5<=0,"",H5-F5) | J5: =IF(F5<=0,"",I5/F5)
B6: =IF(A6="","",INDEX('Trade Log'!D:D,MATCH(A6,'Trade Log'!C:C,0))) | C6: =IF(A6="","",INDEX('Trade Log'!E:E,MATCH(A6,'Trade Log'!C:C,0))) | D6: =IF(A6="","",SUMIFS('Trade Log'!G:G,'Trade Log'!C:C,A6,'Trade Log'!F:F,"BUY")-SUMIFS('Trade Log'!G:G,'Trade Log'!C:C,A6,'Trade Log'!F:F,"SELL")) | E6: =IF(D6<=0,"",SUMIFS('Trade Log'!K:K,'Trade Log'!C:C,A6,'Trade Log'!F:F,"BUY")/SUMIFS('Trade Log'!G:G,'Trade Log'!C:C,A6,'Trade Log'!F:F,"BUY")) | F6: =IF(D6<=0,"",D6*E6) | H6: =IF(D6<=0,"",D6*G6) | I6: =IF(D6<=0,"",H6-F6) | J6: =IF(F6<=0,"",I6/F6)
B7: =IF(A7="","",INDEX('Trade Log'!D:D,MATCH(A7,'Trade Log'!C:C,0))) | C7: =IF(A7="","",INDEX('Trade Log'!E:E,MATCH(A7,'Trade Log'!C:C,0))) | D7: =IF(A7="","",SUMIFS('Trade Log'!G:G,'Trade Log'!C:C,A7,'Trade Log'!F:F,"BUY")-SUMIFS('Trade Log'!G:G,'Trade Log'!C:C,A7,'Trade Log'!F:F,"SELL")) | E7: =IF(D7<=0,"",SUMIFS('Trade Log'!K:K,'Trade Log'!C:C,A7,'Trade Log'!F:F,"BUY")/SUMIFS('Trade Log'!G:G,'Trade Log'!C:C,A7,'Trade Log'!F:F,"BUY")) | F7: =IF(D7<=0,"",D7*E7) | H7: =IF(D7<=0,"",D7*G7) | I7: =IF(D7<=0,"",H7-F7) | J7: =IF(F7<=0,"",I7/F7)
B8: =IF(A8="","",INDEX('Trade Log'!D:D,MATCH(A8,'Trade Log'!C:C,0))) | C8: =IF(A8="","",INDEX('Trade Log'!E:E,MATCH(A8,'Trade Log'!C:C,0))) | D8: =IF(A8="","",SUMIFS('Trade Log'!G:G,'Trade Log'!C:C,A8,'Trade Log'!F:F,"BUY")-SUMIFS('Trade Log'!G:G,'Trade Log'!C:C,A8,'Trade Log'!F:F,"SELL")) | E8: =IF(D8<=0,"",SUMIFS('Trade Log'!K:K,'Trade Log'!C:C,A8,'Trade Log'!F:F,"BUY")/SUMIFS('Trade Log'!G:G,'Trade Log'!C:C,A8,'Trade Log'!F:F,"BUY")) | F8: =IF(D8<=0,"",D8*E8) | H8: =IF(D8<=0,"",D8*G8) | I8: =IF(D8<=0,"",H8-F8) | J8: =IF(F8<=0,"",I8/F8)
B9: =IF(A9="","",INDEX('Trade Log'!D:D,MATCH(A9,'Trade Log'!C:C,0))) | C9: =IF(A9="","",INDEX('Trade Log'!E:E,MATCH(A9,'Trade Log'!C:C,0))) | D9: =IF(A9="","",SUMIFS('Trade Log'!G:G,'Trade Log'!C:C,A9,'Trade Log'!F:F,"BUY")-SUMIFS('Trade Log'!G:G,'Trade Log'!C:C,A9,'Trade Log'!F:F,"SELL")) | E9: =IF(D9<=0,"",SUMIFS('Trade Log'!K:K,'Trade Log'!C:C,A9,'Trade Log'!F:F,"BUY")/SUMIFS('Trade Log'!G:G,'Trade Log'!C:C,A9,'Trade Log'!F:F,"BUY")) | F9: =IF(D9<=0,"",D9*E9) | H9: =IF(D9<=0,"",D9*G9) | I9: =IF(D9<=0,"",H9-F9) | J9: =IF(F9<=0,"",I9/F9)
B10: =IF(A10="","",INDEX('Trade Log'!D:D,MATCH(A10,'Trade Log'!C:C,0))) | C10: =IF(A10="","",INDEX('Trade Log'!E:E,MATCH(A10,'Trade Log'!C:C,0))) | D10: =IF(A10="","",SUMIFS('Trade Log'!G:G,'Trade Log'!C:C,A10,'Trade Log'!F:F,"BUY")-SUMIFS('Trade Log'!G:G,'Trade Log'!C:C,A10,'Trade Log'!F:F,"SELL")) | E10: =IF(D10<=0,"",SUMIFS('Trade Log'!K:K,'Trade Log'!C:C,A10,'Trade Log'!F:F,"BUY")/SUMIFS('Trade Log'!G:G,'Trade Log'!C:C,A10,'Trade Log'!F:F,"BUY")) | F10: =IF(D10<=0,"",D10*E10) | H10: =IF(D10<=0,"",D10*G10) | I10: =IF(D10<=0,"",H10-F10) | J10: =IF(F10<=0,"",I10/F10)
B11: =IF(A11="","",INDEX('Trade Log'!D:D,MATCH(A11,'Trade Log'!C:C,0))) | C11: =IF(A11="","",INDEX('Trade Log'!E:E,MATCH(A11,'Trade Log'!C:C,0))) | D11: =IF(A11="","",SUMIFS('Trade Log'!G:G,'Trade Log'!C:C,A11,'Trade Log'!F:F,"BUY")-SUMIFS('Trade Log'!G:G,'Trade Log'!C:C,A11,'Trade Log'!F:F,"SELL")) | E11: =IF(D11<=0,"",SUMIFS('Trade Log'!K:K,'Trade Log'!C:C,A11,'Trade Log'!F:F,"BUY")/SUMIFS('Trade Log'!G:G,'Trade Log'!C:C,A11,'Trade Log'!F:F,"BUY")) | F11: =IF(D11<=0,"",D11*E11) | H11: =IF(D11<=0,"",D11*G11) | I11: =IF(D11<=0,"",H11-F11) | J11: =IF(F11<=0,"",I11/F11)
B12: =IF(A12="","",INDEX('Trade Log'!D:D,MATCH(A12,'Trade Log'!C:C,0))) | C12: =IF(A12="","",INDEX('Trade Log'!E:E,MATCH(A12,'Trade Log'!C:C,0))) | D12: =IF(A12="","",SUMIFS('Trade Log'!G:G,'Trade Log'!C:C,A12,'Trade Log'!F:F,"BUY")-SUMIFS('Trade Log'!G:G,'Trade Log'!C:C,A12,'Trade Log'!F:F,"SELL")) | E12: =IF(D12<=0,"",SUMIFS('Trade Log'!K:K,'Trade Log'!C:C,A12,'Trade Log'!F:F,"BUY")/SUMIFS('Trade Log'!G:G,'Trade Log'!C:C,A12,'Trade Log'!F:F,"BUY")) | F12: =IF(D12<=0,"",D12*E12) | H12: =IF(D12<=0,"",D12*G12) | I12: =IF(D12<=0,"",H12-F12) | J12: =IF(F12<=0,"",I12/F12)
B13: =IF(A13="","",INDEX('Trade Log'!D:D,MATCH(A13,'Trade Log'!C:C,0))) | C13: =IF(A13="","",INDEX('Trade Log'!E:E,MATCH(A13,'Trade Log'!C:C,0))) | D13: =IF(A13="","",SUMIFS('Trade Log'!G:G,'Trade Log'!C:C,A13,'Trade Log'!F:F,"BUY")-SUMIFS('Trade Log'!G:G,'Trade Log'!C:C,A13,'Trade Log'!F:F,"SELL")) | E13: =IF(D13<=0,"",SUMIFS('Trade Log'!K:K,'Trade Log'!C:C,A13,'Trade Log'!F:F,"BUY")/SUMIFS('Trade Log'!G:G,'Trade Log'!C:C,A13,'Trade Log'!F:F,"BUY")) | F13: =IF(D13<=0,"",D13*E13) | H13: =IF(D13<=0,"",D13*G13) | I13: =IF(D13<=0,"",H13-F13) | J13: =IF(F13<=0,"",I13/F13)
B14: =IF(A14="","",INDEX('Trade Log'!D:D,MATCH(A14,'Trade Log'!C:C,0))) | C14: =IF(A14="","",INDEX('Trade Log'!E:E,MATCH(A14,'Trade Log'!C:C,0))) | D14: =IF(A14="","",SUMIFS('Trade Log'!G:G,'Trade Log'!C:C,A14,'Trade Log'!F:F,"BUY")-SUMIFS('Trade Log'!G:G,'Trade Log'!C:C,A14,'Trade Log'!F:F,"SELL")) | E14: =IF(D14<=0,"",SUMIFS('Trade Log'!K:K,'Trade Log'!C:C,A14,'Trade Log'!F:F,"BUY")/SUMIFS('Trade Log'!G:G,'Trade Log'!C:C,A14,'Trade Log'!F:F,"BUY")) | F14: =IF(D14<=0,"",D14*E14) | H14: =IF(D14<=0,"",D14*G14) | I14: =IF(D14<=0,"",H14-F14) | J14: =IF(F14<=0,"",I14/F14)
B15: =IF(A15="","",INDEX('Trade Log'!D:D,MATCH(A15,'Trade Log'!C:C,0))) | C15: =IF(A15="","",INDEX('Trade Log'!E:E,MATCH(A15,'Trade Log'!C:C,0))) | D15: =IF(A15="","",SUMIFS('Trade Log'!G:G,'Trade Log'!C:C,A15,'Trade Log'!F:F,"BUY")-SUMIFS('Trade Log'!G:G,'Trade Log'!C:C,A15,'Trade Log'!F:F,"SELL")) | E15: =IF(D15<=0,"",SUMIFS('Trade Log'!K:K,'Trade Log'!C:C,A15,'Trade Log'!F:F,"BUY")/SUMIFS('Trade Log'!G:G,'Trade Log'!C:C,A15,'Trade Log'!F:F,"BUY")) | F15: =IF(D15<=0,"",D15*E15) | H15: =IF(D15<=0,"",D15*G15) | I15: =IF(D15<=0,"",H15-F15) | J15: =IF(F15<=0,"",I15/F15)
B16: =IF(A16="","",INDEX('Trade Log'!D:D,MATCH(A16,'Trade Log'!C:C,0))) | C16: =IF(A16="","",INDEX('Trade Log'!E:E,MATCH(A16,'Trade Log'!C:C,0))) | D16: =IF(A16="","",SUMIFS('Trade Log'!G:G,'Trade Log'!C:C,A16,'Trade Log'!F:F,"BUY")-SUMIFS('Trade Log'!G:G,'Trade Log'!C:C,A16,'Trade Log'!F:F,"SELL")) | E16: =IF(D16<=0,"",SUMIFS('Trade Log'!K:K,'Trade Log'!C:C,A16,'Trade Log'!F:F,"BUY")/SUMIFS('Trade Log'!G:G,'Trade Log'!C:C,A16,'Trade Log'!F:F,"BUY")) | F16: =IF(D16<=0,"",D16*E16) | H16: =IF(D16<=0,"",D16*G16) | I16: =IF(D16<=0,"",H16-F16) | J16: =IF(F16<=0,"",I16/F16)
B17: =IF(A17="","",INDEX('Trade Log'!D:D,MATCH(A17,'Trade Log'!C:C,0))) | C17: =IF(A17="","",INDEX('Trade Log'!E:E,MATCH(A17,'Trade Log'!C:C,0))) | D17: =IF(A17="","",SUMIFS('Trade Log'!G:G,'Trade Log'!C:C,A17,'Trade Log'!F:F,"BUY")-SUMIFS('Trade Log'!G:G,'Trade Log'!C:C,A17,'Trade Log'!F:F,"SELL")) | E17: =IF(D17<=0,"",SUMIFS('Trade Log'!K:K,'Trade Log'!C:C,A17,'Trade Log'!F:F,"BUY")/SUMIFS('Trade Log'!G:G,'Trade Log'!C:C,A17,'Trade Log'!F:F,"BUY")) | F17: =IF(D17<=0,"",D17*E17) | H17: =IF(D17<=0,"",D17*G17) | I17: =IF(D17<=0,"",H17-F17) | J17: =IF(F17<=0,"",I17/F17)
... B54: =IF(A54="","",INDEX('Trade Log'!D:D,MATCH(A54,'Trade Log'!C:C,0))) | C54: =IF(A54="","",INDEX('Trade Log'!E:E,MATCH(A54,'Trade Log'!C:C,0))) | D54: =IF(A54="","",SUMIFS('Trade Log'!G:G,'Trade Log'!C:C,A54,'Trade Log'!F:F,"BUY")-SUMIFS('Trade Log'!G:G,'Trade Log'!C:C,A54,'Trade Log'!F:F,"SELL")) | E54: =IF(D54<=0,"",SUMIFS('Trade Log'!K:K,'Trade Log'!C:C,A54,'Trade Log'!F:F,"BUY")/SUMIFS('Trade Log'!G:G,'Trade Log'!C:C,A54,'Trade Log'!F:F,"BUY")) | F54: =IF(D54<=0,"",D54*E54) | H54: =IF(D54<=0,"",D54*G54) | I54: =IF(D54<=0,"",H54-F54) | J54: =IF(F54<=0,"",I54/F54)
A57: Totals | F57: =SUM(F5:F54) | H57: =SUM(H5:H54) | I57: =SUM(I5:I54)

Sheet Closed Trades
A1: Round-trip trades (enter Position ID from Trade Log)
A3: Position ID | B3: Symbol | C3: Segment | D3: Buy date | E3: Sell date | F3: Qty | G3: Buy avg (₹) | H3: Sell avg (₹) | I3: Gross P&L (₹) | J3: Total charges (₹) | K3: Net P&L (₹) | L3: Return % | M3: Hold days
A4: T001 | B4: =IF(A4="","",INDEX('Trade Log'!C:C,MATCH(A4,'Trade Log'!I:I,0))) | C4: =IF(A4="","",INDEX('Trade Log'!E:E,MATCH(A4,'Trade Log'!I:I,0))) | D4: =IF(A4="","",MINIFS('Trade Log'!B:B,'Trade Log'!I:I,A4,'Trade Log'!F:F,"BUY")) | E4: =IF(A4="","",MAXIFS('Trade Log'!B:B,'Trade Log'!I:I,A4,'Trade Log'!F:F,"SELL")) | F4: =IF(A4="","",MIN(SUMIFS('Trade Log'!G:G,'Trade Log'!I:I,A4,'Trade Log'!F:F,"BUY"),SUMIFS('Trade Log'!G:G,'Trade Log'!I:I,A4,'Trade Log'!F:F,"SELL"))) | G4: =IF(A4="","",SUMIFS('Trade Log'!K:K,'Trade Log'!I:I,A4,'Trade Log'!F:F,"BUY")/SUMIFS('Trade Log'!G:G,'Trade Log'!I:I,A4,'Trade Log'!F:F,"BUY")) | H4: =IF(A4="","",SUMIFS('Trade Log'!K:K,'Trade Log'!I:I,A4,'Trade Log'!F:F,"SELL")/SUMIFS('Trade Log'!G:G,'Trade Log'!I:I,A4,'Trade Log'!F:F,"SELL")) | I4: =IF(A4="","",(H4-G4)*F4) | J4: =IF(A4="","",SUMIFS('Trade Log'!R:R,'Trade Log'!I:I,A4)) | K4: =IF(A4="","",I4-J4) | L4: =IF(A4="","",IF(G4*F4=0,"",K4/(G4*F4))) | M4: =IF(A4="","",E4-D4)
A5: T002 | B5: =IF(A5="","",INDEX('Trade Log'!C:C,MATCH(A5,'Trade Log'!I:I,0))) | C5: =IF(A5="","",INDEX('Trade Log'!E:E,MATCH(A5,'Trade Log'!I:I,0))) | D5: =IF(A5="","",MINIFS('Trade Log'!B:B,'Trade Log'!I:I,A5,'Trade Log'!F:F,"BUY")) | E5: =IF(A5="","",MAXIFS('Trade Log'!B:B,'Trade Log'!I:I,A5,'Trade Log'!F:F,"SELL")) | F5: =IF(A5="","",MIN(SUMIFS('Trade Log'!G:G,'Trade Log'!I:I,A5,'Trade Log'!F:F,"BUY"),SUMIFS('Trade Log'!G:G,'Trade Log'!I:I,A5,'Trade Log'!F:F,"SELL"))) | G5: =IF(A5="","",SUMIFS('Trade Log'!K:K,'Trade Log'!I:I,A5,'Trade Log'!F:F,"BUY")/SUMIFS('Trade Log'!G:G,'Trade Log'!I:I,A5,'Trade Log'!F:F,"BUY")) | H5: =IF(A5="","",SUMIFS('Trade Log'!K:K,'Trade Log'!I:I,A5,'Trade Log'!F:F,"SELL")/SUMIFS('Trade Log'!G:G,'Trade Log'!I:I,A5,'Trade Log'!F:F,"SELL")) | I5: =IF(A5="","",(H5-G5)*F5) | J5: =IF(A5="","",SUMIFS('Trade Log'!R:R,'Trade Log'!I:I,A5)) | K5: =IF(A5="","",I5-J5) | L5: =IF(A5="","",IF(G5*F5=0,"",K5/(G5*F5))) | M5: =IF(A5="","",E5-D5)
B6: =IF(A6="","",INDEX('Trade Log'!C:C,MATCH(A6,'Trade Log'!I:I,0))) | C6: =IF(A6="","",INDEX('Trade Log'!E:E,MATCH(A6,'Trade Log'!I:I,0))) | D6: =IF(A6="","",MINIFS('Trade Log'!B:B,'Trade Log'!I:I,A6,'Trade Log'!F:F,"BUY")) | E6: =IF(A6="","",MAXIFS('Trade Log'!B:B,'Trade Log'!I:I,A6,'Trade Log'!F:F,"SELL")) | F6: =IF(A6="","",MIN(SUMIFS('Trade Log'!G:G,'Trade Log'!I:I,A6,'Trade Log'!F:F,"BUY"),SUMIFS('Trade Log'!G:G,'Trade Log'!I:I,A6,'Trade Log'!F:F,"SELL"))) | G6: =IF(A6="","",SUMIFS('Trade Log'!K:K,'Trade Log'!I:I,A6,'Trade Log'!F:F,"BUY")/SUMIFS('Trade Log'!G:G,'Trade Log'!I:I,A6,'Trade Log'!F:F,"BUY")) | H6: =IF(A6="","",SUMIFS('Trade Log'!K:K,'Trade Log'!I:I,A6,'Trade Log'!F:F,"SELL")/SUMIFS('Trade Log'!G:G,'Trade Log'!I:I,A6,'Trade Log'!F:F,"SELL")) | I6: =IF(A6="","",(H6-G6)*F6) | J6: =IF(A6="","",SUMIFS('Trade Log'!R:R,'Trade Log'!I:I,A6)) | K6: =IF(A6="","",I6-J6) | L6: =IF(A6="","",IF(G6*F6=0,"",K6/(G6*F6))) | M6: =IF(A6="","",E6-D6)
B7: =IF(A7="","",INDEX('Trade Log'!C:C,MATCH(A7,'Trade Log'!I:I,0))) | C7: =IF(A7="","",INDEX('Trade Log'!E:E,MATCH(A7,'Trade Log'!I:I,0))) | D7: =IF(A7="","",MINIFS('Trade Log'!B:B,'Trade Log'!I:I,A7,'Trade Log'!F:F,"BUY")) | E7: =IF(A7="","",MAXIFS('Trade Log'!B:B,'Trade Log'!I:I,A7,'Trade Log'!F:F,"SELL")) | F7: =IF(A7="","",MIN(SUMIFS('Trade Log'!G:G,'Trade Log'!I:I,A7,'Trade Log'!F:F,"BUY"),SUMIFS('Trade Log'!G:G,'Trade Log'!I:I,A7,'Trade Log'!F:F,"SELL"))) | G7: =IF(A7="","",SUMIFS('Trade Log'!K:K,'Trade Log'!I:I,A7,'Trade Log'!F:F,"BUY")/SUMIFS('Trade Log'!G:G,'Trade Log'!I:I,A7,'Trade Log'!F:F,"BUY")) | H7: =IF(A7="","",SUMIFS('Trade Log'!K:K,'Trade Log'!I:I,A7,'Trade Log'!F:F,"SELL")/SUMIFS('Trade Log'!G:G,'Trade Log'!I:I,A7,'Trade Log'!F:F,"SELL")) | I7: =IF(A7="","",(H7-G7)*F7) | J7: =IF(A7="","",SUMIFS('Trade Log'!R:R,'Trade Log'!I:I,A7)) | K7: =IF(A7="","",I7-J7) | L7: =IF(A7="","",IF(G7*F7=0,"",K7/(G7*F7))) | M7: =IF(A7="","",E7-D7)
B8: =IF(A8="","",INDEX('Trade Log'!C:C,MATCH(A8,'Trade Log'!I:I,0))) | C8: =IF(A8="","",INDEX('Trade Log'!E:E,MATCH(A8,'Trade Log'!I:I,0))) | D8: =IF(A8="","",MINIFS('Trade Log'!B:B,'Trade Log'!I:I,A8,'Trade Log'!F:F,"BUY")) | E8: =IF(A8="","",MAXIFS('Trade Log'!B:B,'Trade Log'!I:I,A8,'Trade Log'!F:F,"SELL")) | F8: =IF(A8="","",MIN(SUMIFS('Trade Log'!G:G,'Trade Log'!I:I,A8,'Trade Log'!F:F,"BUY"),SUMIFS('Trade Log'!G:G,'Trade Log'!I:I,A8,'Trade Log'!F:F,"SELL"))) | G8: =IF(A8="","",SUMIFS('Trade Log'!K:K,'Trade Log'!I:I,A8,'Trade Log'!F:F,"BUY")/SUMIFS('Trade Log'!G:G,'Trade Log'!I:I,A8,'Trade Log'!F:F,"BUY")) | H8: =IF(A8="","",SUMIFS('Trade Log'!K:K,'Trade Log'!I:I,A8,'Trade Log'!F:F,"SELL")/SUMIFS('Trade Log'!G:G,'Trade Log'!I:I,A8,'Trade Log'!F:F,"SELL")) | I8: =IF(A8="","",(H8-G8)*F8) | J8: =IF(A8="","",SUMIFS('Trade Log'!R:R,'Trade Log'!I:I,A8)) | K8: =IF(A8="","",I8-J8) | L8: =IF(A8="","",IF(G8*F8=0,"",K8/(G8*F8))) | M8: =IF(A8="","",E8-D8)
B9: =IF(A9="","",INDEX('Trade Log'!C:C,MATCH(A9,'Trade Log'!I:I,0))) | C9: =IF(A9="","",INDEX('Trade Log'!E:E,MATCH(A9,'Trade Log'!I:I,0))) | D9: =IF(A9="","",MINIFS('Trade Log'!B:B,'Trade Log'!I:I,A9,'Trade Log'!F:F,"BUY")) | E9: =IF(A9="","",MAXIFS('Trade Log'!B:B,'Trade Log'!I:I,A9,'Trade Log'!F:F,"SELL")) | F9: =IF(A9="","",MIN(SUMIFS('Trade Log'!G:G,'Trade Log'!I:I,A9,'Trade Log'!F:F,"BUY"),SUMIFS('Trade Log'!G:G,'Trade Log'!I:I,A9,'Trade Log'!F:F,"SELL"))) | G9: =IF(A9="","",SUMIFS('Trade Log'!K:K,'Trade Log'!I:I,A9,'Trade Log'!F:F,"BUY")/SUMIFS('Trade Log'!G:G,'Trade Log'!I:I,A9,'Trade Log'!F:F,"BUY")) | H9: =IF(A9="","",SUMIFS('Trade Log'!K:K,'Trade Log'!I:I,A9,'Trade Log'!F:F,"SELL")/SUMIFS('Trade Log'!G:G,'Trade Log'!I:I,A9,'Trade Log'!F:F,"SELL")) | I9: =IF(A9="","",(H9-G9)*F9) | J9: =IF(A9="","",SUMIFS('Trade Log'!R:R,'Trade Log'!I:I,A9)) | K9: =IF(A9="","",I9-J9) | L9: =IF(A9="","",IF(G9*F9=0,"",K9/(G9*F9))) | M9: =IF(A9="","",E9-D9)
B10: =IF(A10="","",INDEX('Trade Log'!C:C,MATCH(A10,'Trade Log'!I:I,0))) | C10: =IF(A10="","",INDEX('Trade Log'!E:E,MATCH(A10,'Trade Log'!I:I,0))) | D10: =IF(A10="","",MINIFS('Trade Log'!B:B,'Trade Log'!I:I,A10,'Trade Log'!F:F,"BUY")) | E10: =IF(A10="","",MAXIFS('Trade Log'!B:B,'Trade Log'!I:I,A10,'Trade Log'!F:F,"SELL")) | F10: =IF(A10="","",MIN(SUMIFS('Trade Log'!G:G,'Trade Log'!I:I,A10,'Trade Log'!F:F,"BUY"),SUMIFS('Trade Log'!G:G,'Trade Log'!I:I,A10,'Trade Log'!F:F,"SELL"))) | G10: =IF(A10="","",SUMIFS('Trade Log'!K:K,'Trade Log'!I:I,A10,'Trade Log'!F:F,"BUY")/SUMIFS('Trade Log'!G:G,'Trade Log'!I:I,A10,'Trade Log'!F:F,"BUY")) | H10: =IF(A10="","",SUMIFS('Trade Log'!K:K,'Trade Log'!I:I,A10,'Trade Log'!F:F,"SELL")/SUMIFS('Trade Log'!G:G,'Trade Log'!I:I,A10,'Trade Log'!F:F,"SELL")) | I10: =IF(A10="","",(H10-G10)*F10) | J10: =IF(A10="","",SUMIFS('Trade Log'!R:R,'Trade Log'!I:I,A10)) | K10: =IF(A10="","",I10-J10) | L10: =IF(A10="","",IF(G10*F10=0,"",K10/(G10*F10))) | M10: =IF(A10="","",E10-D10)
B11: =IF(A11="","",INDEX('Trade Log'!C:C,MATCH(A11,'Trade Log'!I:I,0))) | C11: =IF(A11="","",INDEX('Trade Log'!E:E,MATCH(A11,'Trade Log'!I:I,0))) | D11: =IF(A11="","",MINIFS('Trade Log'!B:B,'Trade Log'!I:I,A11,'Trade Log'!F:F,"BUY")) | E11: =IF(A11="","",MAXIFS('Trade Log'!B:B,'Trade Log'!I:I,A11,'Trade Log'!F:F,"SELL")) | F11: =IF(A11="","",MIN(SUMIFS('Trade Log'!G:G,'Trade Log'!I:I,A11,'Trade Log'!F:F,"BUY"),SUMIFS('Trade Log'!G:G,'Trade Log'!I:I,A11,'Trade Log'!F:F,"SELL"))) | G11: =IF(A11="","",SUMIFS('Trade Log'!K:K,'Trade Log'!I:I,A11,'Trade Log'!F:F,"BUY")/SUMIFS('Trade Log'!G:G,'Trade Log'!I:I,A11,'Trade Log'!F:F,"BUY")) | H11: =IF(A11="","",SUMIFS('Trade Log'!K:K,'Trade Log'!I:I,A11,'Trade Log'!F:F,"SELL")/SUMIFS('Trade Log'!G:G,'Trade Log'!I:I,A11,'Trade Log'!F:F,"SELL")) | I11: =IF(A11="","",(H11-G11)*F11) | J11: =IF(A11="","",SUMIFS('Trade Log'!R:R,'Trade Log'!I:I,A11)) | K11: =IF(A11="","",I11-J11) | L11: =IF(A11="","",IF(G11*F11=0,"",K11/(G11*F11))) | M11: =IF(A11="","",E11-D11)
B12: =IF(A12="","",INDEX('Trade Log'!C:C,MATCH(A12,'Trade Log'!I:I,0))) | C12: =IF(A12="","",INDEX('Trade Log'!E:E,MATCH(A12,'Trade Log'!I:I,0))) | D12: =IF(A12="","",MINIFS('Trade Log'!B:B,'Trade Log'!I:I,A12,'Trade Log'!F:F,"BUY")) | E12: =IF(A12="","",MAXIFS('Trade Log'!B:B,'Trade Log'!I:I,A12,'Trade Log'!F:F,"SELL")) | F12: =IF(A12="","",MIN(SUMIFS('Trade Log'!G:G,'Trade Log'!I:I,A12,'Trade Log'!F:F,"BUY"),SUMIFS('Trade Log'!G:G,'Trade Log'!I:I,A12,'Trade Log'!F:F,"SELL"))) | G12: =IF(A12="","",SUMIFS('Trade Log'!K:K,'Trade Log'!I:I,A12,'Trade Log'!F:F,"BUY")/SUMIFS('Trade Log'!G:G,'Trade Log'!I:I,A12,'Trade Log'!F:F,"BUY")) | H12: =IF(A12="","",SUMIFS('Trade Log'!K:K,'Trade Log'!I:I,A12,'Trade Log'!F:F,"SELL")/SUMIFS('Trade Log'!G:G,'Trade Log'!I:I,A12,'Trade Log'!F:F,"SELL")) | I12: =IF(A12="","",(H12-G12)*F12) | J12: =IF(A12="","",SUMIFS('Trade Log'!R:R,'Trade Log'!I:I,A12)) | K12: =IF(A12="","",I12-J12) | L12: =IF(A12="","",IF(G12*F12=0,"",K12/(G12*F12))) | M12: =IF(A12="","",E12-D12)
B13: =IF(A13="","",INDEX('Trade Log'!C:C,MATCH(A13,'Trade Log'!I:I,0))) | C13: =IF(A13="","",INDEX('Trade Log'!E:E,MATCH(A13,'Trade Log'!I:I,0))) | D13: =IF(A13="","",MINIFS('Trade Log'!B:B,'Trade Log'!I:I,A13,'Trade Log'!F:F,"BUY")) | E13: =IF(A13="","",MAXIFS('Trade Log'!B:B,'Trade Log'!I:I,A13,'Trade Log'!F:F,"SELL")) | F13: =IF(A13="","",MIN(SUMIFS('Trade Log'!G:G,'Trade Log'!I:I,A13,'Trade Log'!F:F,"BUY"),SUMIFS('Trade Log'!G:G,'Trade Log'!I:I,A13,'Trade Log'!F:F,"SELL"))) | G13: =IF(A13="","",SUMIFS('Trade Log'!K:K,'Trade Log'!I:I,A13,'Trade Log'!F:F,"BUY")/SUMIFS('Trade Log'!G:G,'Trade Log'!I:I,A13,'Trade Log'!F:F,"BUY")) | H13: =IF(A13="","",SUMIFS('Trade Log'!K:K,'Trade Log'!I:I,A13,'Trade Log'!F:F,"SELL")/SUMIFS('Trade Log'!G:G,'Trade Log'!I:I,A13,'Trade Log'!F:F,"SELL")) | I13: =IF(A13="","",(H13-G13)*F13) | J13: =IF(A13="","",SUMIFS('Trade Log'!R:R,'Trade Log'!I:I,A13)) | K13: =IF(A13="","",I13-J13) | L13: =IF(A13="","",IF(G13*F13=0,"",K13/(G13*F13))) | M13: =IF(A13="","",E13-D13)
B14: =IF(A14="","",INDEX('Trade Log'!C:C,MATCH(A14,'Trade Log'!I:I,0))) | C14: =IF(A14="","",INDEX('Trade Log'!E:E,MATCH(A14,'Trade Log'!I:I,0))) | D14: =IF(A14="","",MINIFS('Trade Log'!B:B,'Trade Log'!I:I,A14,'Trade Log'!F:F,"BUY")) | E14: =IF(A14="","",MAXIFS('Trade Log'!B:B,'Trade Log'!I:I,A14,'Trade Log'!F:F,"SELL")) | F14: =IF(A14="","",MIN(SUMIFS('Trade Log'!G:G,'Trade Log'!I:I,A14,'Trade Log'!F:F,"BUY"),SUMIFS('Trade Log'!G:G,'Trade Log'!I:I,A14,'Trade Log'!F:F,"SELL"))) | G14: =IF(A14="","",SUMIFS('Trade Log'!K:K,'Trade Log'!I:I,A14,'Trade Log'!F:F,"BUY")/SUMIFS('Trade Log'!G:G,'Trade Log'!I:I,A14,'Trade Log'!F:F,"BUY")) | H14: =IF(A14="","",SUMIFS('Trade Log'!K:K,'Trade Log'!I:I,A14,'Trade Log'!F:F,"SELL")/SUMIFS('Trade Log'!G:G,'Trade Log'!I:I,A14,'Trade Log'!F:F,"SELL")) | I14: =IF(A14="","",(H14-G14)*F14) | J14: =IF(A14="","",SUMIFS('Trade Log'!R:R,'Trade Log'!I:I,A14)) | K14: =IF(A14="","",I14-J14) | L14: =IF(A14="","",IF(G14*F14=0,"",K14/(G14*F14))) | M14: =IF(A14="","",E14-D14)
B15: =IF(A15="","",INDEX('Trade Log'!C:C,MATCH(A15,'Trade Log'!I:I,0))) | C15: =IF(A15="","",INDEX('Trade Log'!E:E,MATCH(A15,'Trade Log'!I:I,0))) | D15: =IF(A15="","",MINIFS('Trade Log'!B:B,'Trade Log'!I:I,A15,'Trade Log'!F:F,"BUY")) | E15: =IF(A15="","",MAXIFS('Trade Log'!B:B,'Trade Log'!I:I,A15,'Trade Log'!F:F,"SELL")) | F15: =IF(A15="","",MIN(SUMIFS('Trade Log'!G:G,'Trade Log'!I:I,A15,'Trade Log'!F:F,"BUY"),SUMIFS('Trade Log'!G:G,'Trade Log'!I:I,A15,'Trade Log'!F:F,"SELL"))) | G15: =IF(A15="","",SUMIFS('Trade Log'!K:K,'Trade Log'!I:I,A15,'Trade Log'!F:F,"BUY")/SUMIFS('Trade Log'!G:G,'Trade Log'!I:I,A15,'Trade Log'!F:F,"BUY")) | H15: =IF(A15="","",SUMIFS('Trade Log'!K:K,'Trade Log'!I:I,A15,'Trade Log'!F:F,"SELL")/SUMIFS('Trade Log'!G:G,'Trade Log'!I:I,A15,'Trade Log'!F:F,"SELL")) | I15: =IF(A15="","",(H15-G15)*F15) | J15: =IF(A15="","",SUMIFS('Trade Log'!R:R,'Trade Log'!I:I,A15)) | K15: =IF(A15="","",I15-J15) | L15: =IF(A15="","",IF(G15*F15=0,"",K15/(G15*F15))) | M15: =IF(A15="","",E15-D15)
B16: =IF(A16="","",INDEX('Trade Log'!C:C,MATCH(A16,'Trade Log'!I:I,0))) | C16: =IF(A16="","",INDEX('Trade Log'!E:E,MATCH(A16,'Trade Log'!I:I,0))) | D16: =IF(A16="","",MINIFS('Trade Log'!B:B,'Trade Log'!I:I,A16,'Trade Log'!F:F,"BUY")) | E16: =IF(A16="","",MAXIFS('Trade Log'!B:B,'Trade Log'!I:I,A16,'Trade Log'!F:F,"SELL")) | F16: =IF(A16="","",MIN(SUMIFS('Trade Log'!G:G,'Trade Log'!I:I,A16,'Trade Log'!F:F,"BUY"),SUMIFS('Trade Log'!G:G,'Trade Log'!I:I,A16,'Trade Log'!F:F,"SELL"))) | G16: =IF(A16="","",SUMIFS('Trade Log'!K:K,'Trade Log'!I:I,A16,'Trade Log'!F:F,"BUY")/SUMIFS('Trade Log'!G:G,'Trade Log'!I:I,A16,'Trade Log'!F:F,"BUY")) | H16: =IF(A16="","",SUMIFS('Trade Log'!K:K,'Trade Log'!I:I,A16,'Trade Log'!F:F,"SELL")/SUMIFS('Trade Log'!G:G,'Trade Log'!I:I,A16,'Trade Log'!F:F,"SELL")) | I16: =IF(A16="","",(H16-G16)*F16) | J16: =IF(A16="","",SUMIFS('Trade Log'!R:R,'Trade Log'!I:I,A16)) | K16: =IF(A16="","",I16-J16) | L16: =IF(A16="","",IF(G16*F16=0,"",K16/(G16*F16))) | M16: =IF(A16="","",E16-D16)
B17: =IF(A17="","",INDEX('Trade Log'!C:C,MATCH(A17,'Trade Log'!I:I,0))) | C17: =IF(A17="","",INDEX('Trade Log'!E:E,MATCH(A17,'Trade Log'!I:I,0))) | D17: =IF(A17="","",MINIFS('Trade Log'!B:B,'Trade Log'!I:I,A17,'Trade Log'!F:F,"BUY")) | E17: =IF(A17="","",MAXIFS('Trade Log'!B:B,'Trade Log'!I:I,A17,'Trade Log'!F:F,"SELL")) | F17: =IF(A17="","",MIN(SUMIFS('Trade Log'!G:G,'Trade Log'!I:I,A17,'Trade Log'!F:F,"BUY"),SUMIFS('Trade Log'!G:G,'Trade Log'!I:I,A17,'Trade Log'!F:F,"SELL"))) | G17: =IF(A17="","",SUMIFS('Trade Log'!K:K,'Trade Log'!I:I,A17,'Trade Log'!F:F,"BUY")/SUMIFS('Trade Log'!G:G,'Trade Log'!I:I,A17,'Trade Log'!F:F,"BUY")) | H17: =IF(A17="","",SUMIFS('Trade Log'!K:K,'Trade Log'!I:I,A17,'Trade Log'!F:F,"SELL")/SUMIFS('Trade Log'!G:G,'Trade Log'!I:I,A17,'Trade Log'!F:F,"SELL")) | I17: =IF(A17="","",(H17-G17)*F17) | J17: =IF(A17="","",SUMIFS('Trade Log'!R:R,'Trade Log'!I:I,A17)) | K17: =IF(A17="","",I17-J17) | L17: =IF(A17="","",IF(G17*F17=0,"",K17/(G17*F17))) | M17: =IF(A17="","",E17-D17)
... B103: =IF(A103="","",INDEX('Trade Log'!C:C,MATCH(A103,'Trade Log'!I:I,0))) | C103: =IF(A103="","",INDEX('Trade Log'!E:E,MATCH(A103,'Trade Log'!I:I,0))) | D103: =IF(A103="","",MINIFS('Trade Log'!B:B,'Trade Log'!I:I,A103,'Trade Log'!F:F,"BUY")) | E103: =IF(A103="","",MAXIFS('Trade Log'!B:B,'Trade Log'!I:I,A103,'Trade Log'!F:F,"SELL")) | F103: =IF(A103="","",MIN(SUMIFS('Trade Log'!G:G,'Trade Log'!I:I,A103,'Trade Log'!F:F,"BUY"),SUMIFS('Trade Log'!G:G,'Trade Log'!I:I,A103,'Trade Log'!F:F,"SELL"))) | G103: =IF(A103="","",SUMIFS('Trade Log'!K:K,'Trade Log'!I:I,A103,'Trade Log'!F:F,"BUY")/SUMIFS('Trade Log'!G:G,'Trade Log'!I:I,A103,'Trade Log'!F:F,"BUY")) | H103: =IF(A103="","",SUMIFS('Trade Log'!K:K,'Trade Log'!I:I,A103,'Trade Log'!F:F,"SELL")/SUMIFS('Trade Log'!G:G,'Trade Log'!I:I,A103,'Trade Log'!F:F,"SELL")) | I103: =IF(A103="","",(H103-G103)*F103) | J103: =IF(A103="","",SUMIFS('Trade Log'!R:R,'Trade Log'!I:I,A103)) | K103: =IF(A103="","",I103-J103) | L103: =IF(A103="","",IF(G103*F103=0,"",K103/(G103*F103))) | M103: =IF(A103="","",E103-D103)

Sheet Summary
A1: Paper trading dashboard
A4: Metric | B4: Value
A5: Starting capital (₹) | B5: =Settings!C4
A6: Cash after all trades (₹) | B6: =Settings!C4+SUM('Trade Log'!S:S)
A7: Invested in open positions (₹) | B7: ='Open Positions'!F57
A8: Portfolio value (cash + holdings) | B8: =B5+B6+'Open Positions'!H57
A9: Total realized P&L (₹) | B9: =SUM('Closed Trades'!K:K)
A10: Total unrealized P&L (₹) | B10: ='Open Positions'!I57
A11: Total P&L (realized + unrealized) | B11: =B9+B10
A12: Return on starting capital % | B12: =IF(Settings!C4=0,"",B11/Settings!C4)
A13: Closed trades (count) | B13: =COUNTIF('Closed Trades'!A4:A103,"?*")
A14: Winning trades | B14: =COUNTIF('Closed Trades'!K4:K103,">0")
A15: Losing trades | B15: =COUNTIF('Closed Trades'!K4:K103,"<0")
A16: Win rate % | B16: =IF(B14=0,"",B15/B14)
A17: Total brokerage paid (₹) | B17: =SUM('Trade Log'!L:L)
A18: Total charges paid (₹) | B18: =SUM('Trade Log'!R:R)
A20: Last updated: enter trades in Trade Log; update LTP on Open Positions for live MTM.
